deswag/__init__.py
deswag/cli.py
deswag/exceptions.py
deswag/openapi.py
deswag/schemas.py
deswag/templater.py
deswag-0.1.0.dist-info/METADATA
deswag-0.1.0.dist-info/RECORD
deswag-0.1.0.dist-info/WHEEL
deswag-0.1.0.dist-info/entry_points.txt
deswag-0.1.0.dist-info/pbr.json
deswag-0.1.0.dist-info/top_level.txt
