Metadata-Version: 2.1
Name: deswag
Version: 0.1.0
Summary: A tool for producing templated files from OpenAPI definitions
Home-page: UNKNOWN
Author: michael mccune
Author-email: msm@opbstudios.com
License: GPL-3.0-or-later
Platform: UNKNOWN
Requires-Dist: jsonschema
Requires-Dist: jinja2
Requires-Dist: pyyaml
